Workbook
Name D6_: Dashboards!$AA$94:$AA$95
Name Electricity: Dashboards!$AA$90
Name Fixed_charge: Dashboards!$AA$92
Name Highest_paid: Dashboards!$AA$94
Name KPI_value: Dashboards!$AA$89
Name Lowest_paid: Dashboards!$AA$95
Name NativeTimeline_Date: #N/A
Name Service_charge: Dashboards!$AA$91
Name Slicer_Apartment_ID: #N/A
Name Slicer_Block: #N/A
Name Total_Revenue: Dashboards!$AA$89
Name Water_Bill: Dashboards!$AA$93

Sheet Raw Data
A1: Estate | B1: Order ID | C1: First Name | D1: Last Name | E1: Meter No | F1: Property Type | G1: Partner Type | H1: House Address | I1: Landlord Name | J1: Landlord Contact | K1: Bill | L1: Type | M1: Bill Type | N1: Duration Start | O1: Duration End | P1: Unit Price | Q1: Total Price | R1: Date | S1: Token | T1: Unit
A2: Alcove Homes | B2: FBX3IRC19APV | C2: MANAGMENT | D2: OFFICE | E2: 47300070555 | F2: Office | G2: Office | H2: MANAGEMENT OFFICE | K2: Electricity Token - Any Amount | L2: BILL | M2: POWER | N2: 45292 | O2: 45322 | P2: 200 | Q2: 200 | R2: 2024-01-09 15:59:24.193036+00:00 | S2: 4171 2599 1916 0300 1098 | T2: 1
A3: Alcove Homes | B3: FB4C7HC7XC56 | C3: Elizabeth | D3: Martin | E3: 47300070704 | F3: Flats | G3: Occupied | H3: Block A, Apt. no. A8. Alcove Homes Estate 17-19 Ishola Street, Adekunle Yaba, Lagos | K3: Service Charge Debt | L3: OUTSTANDING | N3: 45292 | O3: 45322 | P3: 111308.86 | Q3: 111308.86 | R3: 2024-01-11 14:25:59.443921+00:00
A4: Alcove Homes | B4: FBNCBJF57W9S | C4: Barbara | D4: Martinez | E4: 47300025708 | F4: Office | G4: Office - No Water | H4: Block_D Common_Area | K4: Electricity Token - Any Amount | L4: BILL | M4: POWER | N4: 45292 | O4: 45322 | P4: 50000 | Q4: 50000 | R4: 2024-01-16 09:10:51.479427+00:00 | S4: 5765 5477 1290 4259 1775 | T4: 263
A5: Alcove Homes | B5: FBNCBJF57W9S | C5: Power_House | D5: Common_Area | E5: 47300025708 | F5: Office | G5: Office - No Water | H5: Block_D Common_Area | K5: Monthly Access Fee | L5: BILL | M5: SERVICE | N5: 45292 | O5: 45322 | P5: 500 | Q5: 500 | R5: 2024-01-16 09:10:51.479427+00:00
A6: Alcove Homes | B6: FBNCBJF57W9S | C6: Patricia | D6: Williams | E6: 47300025708 | F6: Office | G6: Office - No Water | H6: Block_D Common_Area | K6: Monthly Water Bill | L6: BILL | M6: SERVICE | N6: 45292 | O6: 45322 | P6: 10000 | Q6: 10000 | R6: 2024-01-16 09:10:51.479427+00:00
A7: Alcove Homes | B7: FBIUG35BP7HT | C7: Block_D | D7: Common_Area | E7: 47300086445 | F7: Flats | G7: Occupied | H7: Block B, Apt. no. B5. Alcove Homes Estate 17-19 Ishola Street, Adekunle Yaba, Lagos | I7: Cranleigh Investment Limited | J7: House 5, 5th Avenue Gwarimpa Estate. Abuja FCT, Tel: 08145774497 | K7: Electricity Token - Any Amount | L7: BILL | M7: POWER | N7: 45292 | O7: 45322 | P7: 25000 | Q7: 25000 | R7: 2024-01-16 15:32:55.241478+00:00 | S7: 1955 4821 7035 2914 4034 | T7: 131.5
A8: Alcove Homes | B8: FBIUG35BP7HT | C8: Barbara | D8: Martinez | E8: 47300086445 | F8: Flats | G8: Occupied | H8: Block B, Apt. no. B5. Alcove Homes Estate 17-19 Ishola Street, Adekunle Yaba, Lagos | I8: Cranleigh Investment Limited | J8: House 5, 5th Avenue Gwarimpa Estate. Abuja FCT, Tel: 08145774497 | K8: Monthly Access Fee | L8: BILL | M8: SERVICE | N8: 45292 | O8: 45322 | P8: 500 | Q8: 500 | R8: 2024-01-16 15:32:55.241478+00:00
A9: Alcove Homes | B9: FBSQ2CO2IRP2 | C9: Power_House | D9: Common_Area | E9: 47300026094 | F9: Office | G9: Office - No Water | H9: Power_House Common_Area | K9: Electricity Token - Any Amount | L9: BILL | M9: POWER | N9: 45292 | O9: 45322 | P9: 100000 | Q9: 100000 | R9: 2024-01-16 16:17:49.584000+00:00 | S9: 1481 9068 3005 1342 8693 | T9: 526.3
A10: Alcove Homes | B10: FBSQ2CO2IRP2 | C10: Patricia | D10: Williams | E10: 47300026094 | F10: Office | G10: Office - No Water | H10: Power_House Common_Area | K10: Monthly Access Fee | L10: BILL | M10: SERVICE | N10: 45292 | O10: 45322 | P10: 500 | Q10: 500 | R10: 2024-01-16 16:17:49.584000+00:00
A11: Alcove Homes | B11: FBFCDK7M98DQ | C11: Block_D | D11: Common_Area | E11: 47300070563 | F11: Flats | G11: Occupied | H11: Block C, Apt. no. C3. Alcove Homes Estate 17-19 Ishola Street, Adekunle Yaba, Lagos | K11: Electricity Token - Any Amount | L11: BILL | M11: POWER | N11: 45292 | O11: 45322 | P11: 40000 | Q11: 40000 | R11: 2024-01-16 17:12:15.909679+00:00 | S11: 3446 6037 9260 8339 9302 | T11: 210.5
A12: Alcove Homes | B12: FBFCDK7M98DQ | C12: Barbara | D12: Martinez | E12: 47300070563 | F12: Flats | G12: Occupied | H12: Block C, Apt. no. C3. Alcove Homes Estate 17-19 Ishola Street, Adekunle Yaba, Lagos | K12: Monthly Access Fee | L12: BILL | M12: SERVICE | N12: 45292 | O12: 45322 | P12: 500 | Q12: 500 | R12: 2024-01-16 17:12:15.909679+00:00
A13: Alcove Homes | B13: FBFCDK7M98DQ | C13: Barbara | D13: Martinez | E13: 47300070563 | F13: Flats | G13: Occupied | H13: Block C, Apt. no. C3. Alcove Homes Estate 17-19 Ishola Street, Adekunle Yaba, Lagos | K13: Monthly Service Charge | L13: BILL | M13: SERVICE | N13: 45292 | O13: 45322 | P13: 145500 | Q13: 145500
A14: Alcove Homes | B14: FBFCDK7M98DQ | C14: Block_D | D14: Common_Area | E14: 47300070563 | F14: Flats | G14: Occupied | H14: Block C, Apt. no. C3. Alcove Homes Estate 17-19 Ishola Street, Adekunle Yaba, Lagos | K14: Monthly Water Bill | L14: BILL | M14: SERVICE | Q14: 10000 | R14: 2024-01-16 17:12:15.909679+00:00
A15: Alcove Homes | B15: FBJP8CYMRKX3 | C15: Apartment | D15: A4 | E15: 47300070795 | F15: Flats | G15: Occupied - Prepaid SC and Water | H15: Block B, Apt. no. B4. Alcove Homes Estate 17-19 Ishola Street, Adekunle Yaba, Lagos | K15: Electricity Token - Any Amount | L15: BILL | M15: POWER | N15: 45292 | O15: 45322 | P15: 75000 | Q15: 75000 | R15: 2024-01-17 12:59:02.748133+00:00 | S15: 1805 4045 6763 6696 1614 | T15: 394.7
A16: Alcove Homes | B16: FBJP8CYMRKX3 | C16: Andrew | D16: Allen | E16: 47300070795 | F16: Flats | G16: Occupied - Prepaid SC and Water | H16: Block B, Apt. no. B4. Alcove Homes Estate 17-19 Ishola Street, Adekunle Yaba, Lagos | K16: Monthly Access Fee | L16: BILL | M16: SERVICE | N16: 45292 | O16: 45322 | P16: 500 | Q16: 500 | R16: 2024-01-17 12:59:02.748133+00:00
A17: Alcove Homes | B17: FBJP8CYMRKX3 | C17: Andrew | D17: Allen | E17: 47300070795 | F17: Flats | G17: Occupied - Prepaid SC and Water | H17: Block B, Apt. no. B4. Alcove Homes Estate 17-19 Ishola Street, Adekunle Yaba, Lagos | K17: Monthly Service Charge | L17: BILL | M17: SERVICE | N17: 45292 | O17: 45322 | P17: 145500 | Q17: 145500 | R17: 2024-01-17 12:59:02.748133+00:00
A18: Alcove Homes | B18: FBJP8CYMRKX3 | C18: Andrew | D18: Allen | E18: 47300070795 | F18: Flats | G18: Occupied - Prepaid SC and Water | H18: Block B, Apt. no. B4. Alcove Homes Estate 17-19 Ishola Street, Adekunle Yaba, Lagos | K18: Monthly Water Bill | L18: BILL | M18: SERVICE | N18: 45292 | O18: 45322 | P18: 10000 | Q18: 10000 | R18: 2024-01-17 12:59:02.748133+00:00
A19: Alcove Homes | B19: FBW7CPUUH2I1 | C19: Andrew | D19: Allen | E19: 47300046282 | F19: Flats | G19: Occupied - Prepaid Water | H19: Block A, Apt. no. A4. Alcove Homes Estate 17-19 Ishola Street, Adekunle Yaba, Lagos | K19: Monthly Access Fee | L19: BILL | M19: SERVICE | N19: 45292 | O19: 45322 | P19: 500 | Q19: 500 | R19: 2024-01-17 15:37:16.652419+00:00
A20: Alcove Homes | B20: FBZWBY2OZT9F | C20: MANAGMENT | D20: OFFICE | E20: 47300070837 | F20: Flats | G20: Occupied - Prepaid SC | H20: Block B, Apt. no. B2. Alcove Homes Estate 17-19 Ishola Street, Adekunle Yaba, Lagos | K20: Electricity Token - Any Amount | L20: BILL | M20: POWER | N20: 45292 | O20: 45322 | P20: 80000 | Q20: 80000 | R20: 2024-01-18 12:56:09.703008+00:00 | S20: 1171 5286 4173 3400 5280 | T20: 421
A21: Alcove Homes | B21: FBZWBY2OZT9F | C21: Richard | D21: Allen | E21: 47300070837 | F21: Flats | G21: Occupied - Prepaid SC | H21: Block B, Apt. no. B2. Alcove Homes Estate 17-19 Ishola Street, Adekunle Yaba, Lagos | K21: Monthly Access Fee | L21: BILL | M21: SERVICE | N21: 45292 | O21: 45322 | P21: 500 | Q21: 500 | R21: 2024-01-18 12:56:09.703008+00:00
A22: Alcove Homes | B22: FBZWBY2OZT9F | C22: Richard | D22: Allen | E22: 47300070837 | F22: Flats | G22: Occupied - Prepaid SC | H22: Block B, Apt. no. B2. Alcove Homes Estate 17-19 Ishola Street, Adekunle Yaba, Lagos | K22: Monthly Service Charge | L22: BILL | M22: SERVICE | N22: 45292 | O22: 45322 | P22: 145500 | Q22: 145500 | R22: 2024-01-18 12:56:09.703008+00:00
A23: Alcove Homes | B23: FBZWBY2OZT9F | C23: MANAGMENT | D23: OFFICE | E23: 47300070837 | F23: Flats | G23: Occupied - Prepaid SC | H23: Block B, Apt. no. B2. Alcove Homes Estate 17-19 Ishola Street, Adekunle Yaba, Lagos | K23: Monthly Water Bill | L23: BILL | M23: SERVICE | N23: 45292 | O23: 45473 | P23: 10000 | Q23: 60000 | R23: 2024-01-18 12:56:09.703008+00:00
A24: Alcove Homes | B24: FB0DAH5B58LU | C24: Richard | D24: Allen | E24: 47300070555 | F24: Office | G24: Office | H24: MANAGEMENT OFFICE | K24: Monthly Access Fee | L24: BILL | M24: SERVICE | N24: 45292 | O24: 45322 | P24: 500 | Q24: 500 | R24: 2024-01-18 13:04:40.863544+00:00
A25: Alcove Homes | B25: FB83EPZM5BGF | C25: Richard | D25: Allen | E25: 47300070555 | F25: Office | G25: Office | H25: MANAGEMENT OFFICE | K25: Extra Power Top Up - Any Amount | L25: BILL | M25: TOP_UP | P25: 20000 | Q25: 20000 | R25: 2024-01-18 13:08:21.396007+00:00 | S25: 1502 5537 3637 7452 5280 | T25: 105.3
A26: Alcove Homes | B26: FB9CEQ2CL52M | C26: Anthony | D26: Robinson | E26: 47300046399 | F26: Flats | G26: Occupied | H26: Block D, Apt. no. D3. Alcove Homes Estate 17-19 Ishola Street, Adekunle Yaba, Lagos | K26: Parking penalty -Undesignated area, forceful removal of car clamps | L26: OUTSTANDING | N26: 45309 | O26: 45310 | P26: 150000 | Q26: 150000 | R26: 2024-01-19 11:46:15.630828+00:00
A27: Alcove Homes | B27: FBCESN2HIEL9 | C27: Donna | D27: Torres | E27: 47300070571 | F27: Terrace | G27: Occupied | H27: Block I, Apt. no. I2. Alcove Homes Estate 17-19 Ishola Street, Adekunle Yaba, Lagos | K27: Electricity Token - Any Amount | L27: BILL | M27: POWER | N27: 45292 | O27: 45322 | P27: 50000 | Q27: 50000 | R27: 2024-01-19 13:26:11.968492+00:00 | S27: 3449 6691 9977 3426 0213 | T27: 263.1
A28: Alcove Homes | B28: FBCESN2HIEL9 | C28: Michael | D28: Wright | E28: 47300070571 | F28: Terrace | G28: Occupied | H28: Block I, Apt. no. I2. Alcove Homes Estate 17-19 Ishola Street, Adekunle Yaba, Lagos | K28: Monthly Access Fee | L28: BILL | M28: SERVICE | N28: 45292 | O28: 45322 | P28: 500 | Q28: 500 | R28: 2024-01-19 13:26:11.968492+00:00
A29: Alcove Homes | B29: FB0Y6MK1WKSR | C29: Donald | D29: Jones | E29: 47300046761 | F29: Terrace | G29: Occupied | H29: Block I, Apt. no. I1. Alcove Homes Estate 17-19 Ishola Street, Adekunle Yaba, Lagos | K29: Electricity Token - Any Amount | L29: BILL | M29: POWER | N29: 45292 | O29: 45322 | P29: 50000 | Q29: 50000 | R29: 2024-01-19 13:26:45.786830+00:00 | S29: 4268 7420 5910 3421 3243 | T29: 263.1
A30: Alcove Homes | B30: FB0Y6MK1WKSR | C30: Paul | D30: Garcia | E30: 47300046761 | F30: Terrace | G30: Occupied | H30: Block I, Apt. no. I1. Alcove Homes Estate 17-19 Ishola Street, Adekunle Yaba, Lagos | K30: Monthly Access Fee | L30: BILL | M30: SERVICE | N30: 45292 | O30: 45322 | P30: 500 | Q30: 500 | R30: 2024-01-19 13:26:45.786830+00:00
A31: Alcove Homes | B31: FBXUB8UT7Z61 | C31: Security_Utilities | D31: Common_Area | E31: 47300025690 | F31: Office | G31: Office - No Water | H31: Security and Utilities Area | K31: Electricity Token - Any Amount | L31: BILL | M31: POWER | N31: 45292 | O31: 45322 | P31: 50000 | Q31: 50000 | R31: 2024-01-19 13:34:02.914179+00:00 | S31: 6141 2937 5192 2139 6399 | T31: 263.2
A32: Alcove Homes | B32: FBXUB8UT7Z61 | C32: Joshua | D32: Harris | E32: 47300025690 | F32: Office | G32: Office - No Water | H32: Security and Utilities Area | K32: Monthly Access Fee | L32: BILL | M32: SERVICE | N32: 45292 | O32: 45322 | P32: 500 | Q32: 500 | R32: 2024-01-19 13:34:02.914179+00:00
A33: Alcove Homes | B33: FBVPK7RDLOEI | C33: Karen | D33: Rodriguez | E33: 47300025708 | F33: Office | G33: Office - No Water | H33: Block_D Common_Area | K33: Extra Power Top Up - Any Amount | L33: BILL | M33: TOP_UP | P33: 500 | Q33: 500 | R33: 2024-01-19 14:34:51.956740+00:00 | S33: 5195 4150 5235 4172 8609 | T33: 2.6
A34: Alcove Homes | B34: FBXBWICH8LAQ | C34: Anthony | D34: Robinson | E34: 47300046647 | F34: Flats | G34: Occupied - Prepaid SC and Water | H34: Block D, Apt. no. D7. Alcove Homes Estate 17-19 Ishola Street, Adekunle Yaba, Lagos | K34: Monthly Access Fee | L34: BILL | M34: SERVICE | N34: 45292 | O34: 45322 | P34: 500 | Q34: 500 | R34: 2024-01-19 14:40:24.298862+00:00
A35: Alcove Homes | B35: FB20FQAKV9UI | C35: Donna | D35: Torres | E35: 47300046647 | F35: Flats | G35: Occupied - Prepaid SC and Water | H35: Block D, Apt. no. D7. Alcove Homes Estate 17-19 Ishola Street, Adekunle Yaba, Lagos | K35: Electricity Token - Any Amount | L35: BILL | M35: POWER | N35: 45292 | O35: 45322 | P35: 90000 | Q35: 90000 | R35: 2024-01-19 14:57:04.868306+00:00 | S35: 6747 8832 0668 6589 1351 | T35: 473.6
A36: Alcove Homes | B36: FBGPF8KEHF2M | C36: Donald | D36: Jones | E36: 47300047066 | F36: Flats | G36: Occupied | H36: Block C, Apt. no. C4. Alcove Homes Estate 17-19 Ishola Street, Adekunle Yaba, Lagos | K36: Electricity Token - Any Amount | L36: BILL | M36: POWER | N36: 45292 | O36: 45322 | P36: 50000 | Q36: 50000 | R36: 2024-01-19 15:28:38.168359+00:00 | S36: 5981 7617 3889 5751 9629 | T36: 263.1
A37: Alcove Homes | B37: FBGPF8KEHF2M | C37: Paul | D37: Garcia | E37: 47300047066 | F37: Flats | G37: Occupied | H37: Block C, Apt. no. C4. Alcove Homes Estate 17-19 Ishola Street, Adekunle Yaba, Lagos | K37: Monthly Access Fee | L37: BILL | M37: SERVICE | N37: 45292 | O37: 45322 | P37: 500 | Q37: 500 | R37: 2024-01-19 15:28:38.168359+00:00
A38: Alcove Homes | B38: FBO6H19ZP0LK | C38: Security_Utilities | D38: Common_Area | E38: 47300046605 | F38: Flats | G38: Occupied - Prepaid Water | H38: Block D, Apt. no. D5. Alcove Homes Estate 17-19 Ishola Street, Adekunle Yaba, Lagos | K38: Monthly Access Fee | L38: BILL | M38: SERVICE | N38: 45292 | O38: 45322 | P38: 500 | Q38: 500 | R38: 2024-01-19 15:31:01.385207+00:00
A39: Alcove Homes | B39: FBJ4DDISRHYC | C39: Joshua | D39: Harris | E39: 47300046399 | F39: Flats | G39: Occupied | H39: Block D, Apt. no. D3. Alcove Homes Estate 17-19 Ishola Street, Adekunle Yaba, Lagos | K39: Electricity Token - Any Amount | L39: BILL | M39: POWER | N39: 45292 | O39: 45322 | P39: 20000 | Q39: 20000 | R39: 2024-01-19 17:50:02.209271+00:00 | S39: 3822 0525 9297 6342 0056 | T39: 105.2
A40: Alcove Homes | B40: FBJ4DDISRHYC | C40: Karen | D40: Rodriguez | E40: 47300046399 | F40: Flats | G40: Occupied | H40: Block D, Apt. no. D3. Alcove Homes Estate 17-19 Ishola Street, Adekunle Yaba, Lagos | K40: Monthly Access Fee | L40: BILL | M40: SERVICE | N40: 45292 | O40: 45322 | P40: 500 | Q40: 500 | R40: 2024-01-19 17:50:02.209271+00:00
A41: Alcove Homes | B41: FB1QUKZJEB98 | C41: Block_D | D41: Common_Area | E41: 47300046720 | F41: Flats | G41: Occupied | H41: Block D, Apt. no. D2. Alcove Homes Estate 17-19 Ishola Street, Adekunle Yaba, Lagos | K41: Electricity Token - Any Amount | L41: BILL | M41: POWER | N41: 45292 | O41: 45322 | P41: 25000 | Q41: 25000 | R41: 2024-01-19 18:57:39.098566+00:00 | S41: 3526 9927 4664 2030 5627 | T41: 131.5
A42: Alcove Homes | B42: FB1QUKZJEB98 | C42: Donna | D42: Torres | E42: 47300046720 | F42: Flats | G42: Occupied | H42: Block D, Apt. no. D2. Alcove Homes Estate 17-19 Ishola Street, Adekunle Yaba, Lagos | K42: Monthly Access Fee | L42: BILL | M42: SERVICE | N42: 45292 | O42: 45322 | P42: 500 | Q42: 500 | R42: 2024-01-19 18:57:39.098566+00:00
A43: Alcove Homes | B43: FBHT20EHB4H6 | C43: Paul | D43: Perez | E43: 47300046977 | F43: Flats | G43: Occupied - Prepaid Water | H43: Block D, Apt. no. D1. Alcove Homes Estate 17-19 Ishola Street, Adekunle Yaba, Lagos | K43: Monthly Service Charge | L43: BILL | M43: SERVICE | N43: 45292 | O43: 45322 | P43: 145500 | Q43: 145500 | R43: 2024-01-19 20:51:59.650364+00:00
A44: Alcove Homes | B44: FB0RTX60IXBX | C44: Susan | D44: Nguyen | E44: 47300046241 | F44: Flats | G44: Occupied - Prepaid SC | H44: Block C, Apt. no. C5. Alcove Homes Estate 17-19 Ishola Street, Adekunle Yaba, Lagos | I44: Dr. Ibikunle Koya | J44: 0 | K44: Water bill August -December 2023 | L44: OUTSTANDING | N44: 45310 | O44: 45316 | P44: 47500 | Q44: 47500 | R44: 2024-01-20 10:38:50.096132+00:00
A45: Alcove Homes | B45: FB0RTX60IXBX | C45: Paul | D45: Torres | E45: 47300046241 | F45: Flats | G45: Occupied - Prepaid SC | H45: Block C, Apt. no. C5. Alcove Homes Estate 17-19 Ishola Street, Adekunle Yaba, Lagos | I45: Dr. Ibikunle Koya | J45: 0 | K45: Water bill August -December 2023 Late payment penalty | L45: OUTSTANDING | N45: 45310 | O45: 45316 | P45: 4750 | Q45: 4750 | R45: 2024-01-20 10:38:50.096132+00:00
A46: Alcove Homes | B46: FB3QW638HYG1 | C46: Paul | D46: Perez | E46: 47300046977 | F46: Flats | G46: Occupied - Prepaid Water | H46: Block D, Apt. no. D1. Alcove Homes Estate 17-19 Ishola Street, Adekunle Yaba, Lagos | K46: Monthly Access Fee | L46: BILL | M46: SERVICE | N46: 45292 | O46: 45322 | P46: 500 | Q46: 500 | R46: 2024-01-20 12:02:53.374754+00:00
A47: Alcove Homes | B47: FB3QW638HYG1 | C47: Susan | D47: Nguyen | E47: 47300046977 | F47: Flats | G47: Occupied - Prepaid Water | H47: Block D, Apt. no. D1. Alcove Homes Estate 17-19 Ishola Street, Adekunle Yaba, Lagos | K47: Monthly Water Bill | L47: BILL | M47: SERVICE | N47: 45292 | O47: 45322 | P47: 10000 | Q47: 10000 | R47: 2024-01-20 12:02:53.374754+00:00
A48: Alcove Homes | B48: FBEJZNM1SKLT | C48: Paul | D48: Torres | E48: 47300070480 | F48: Flats | G48: Occupied | H48: Block B, Apt. no. B1. Alcove Homes Estate 17-19 Ishola Street, Adekunle Yaba, Lagos | K48: Electricity Token - Any Amount | L48: BILL | M48: POWER | N48: 45292 | O48: 45322 | P48: 30000 | Q48: 30000 | R48: 2024-01-20 13:41:35.373991+00:00 | S48: 0034 9594 4959 2515 2336 | T48: 157.8
A49: Alcove Homes | B49: FBEJZNM1SKLT | C49: Susan | D49: Nguyen | E49: 47300070480 | F49: Flats | G49: Occupied | H49: Block B, Apt. no. B1. Alcove Homes Estate 17-19 Ishola Street, Adekunle Yaba, Lagos | K49: Monthly Access Fee | L49: BILL | M49: SERVICE | N49: 45292 | O49: 45322 | P49: 500 | Q49: 500 | R49: 2024-01-20 13:41:35.373991+00:00
A50: Alcove Homes | B50: FBE6JP8GIPM3 | C50: Susan | D50: Nguyen | E50: 47300070688 | F50: Flats | G50: Occupied - Prepaid Water | H50: Block A, Apt. no. A6. Alcove Homes Estate 17-19 Ishola Street, Adekunle Yaba, Lagos | K50: Electricity Token - Any Amount | L50: BILL | M50: POWER | N50: 45292 | O50: 45322 | P50: 50000 | Q50: 50000 | R50: 2024-01-20 23:26:46.893096+00:00 | S50: 3068 6563 8227 5928 0862 | T50: 263.1
A51: Alcove Homes | B51: FBE6JP8GIPM3 | C51: Paul | D51: Perez | E51: 47300070688 | F51: Flats | G51: Occupied - Prepaid Water | H51: Block A, Apt. no. A6. Alcove Homes Estate 17-19 Ishola Street, Adekunle Yaba, Lagos | K51: Monthly Access Fee | L51: BILL | M51: SERVICE | N51: 45292 | O51: 45322 | P51: 500 | Q51: 500 | R51: 2024-01-20 23:26:46.893096+00:00
A52: Alcove Homes | B52: FBE6JP8GIPM3 | C52: Thomas | D52: Sanchez | E52: 47300070688 | F52: Flats | G52: Occupied - Prepaid Water | H52: Block A, Apt. no. A6. Alcove Homes Estate 17-19 Ishola Street, Adekunle Yaba, Lagos | K52: Monthly Service Charge | L52: BILL | M52: SERVICE | N52: 45292 | O52: 45322 | P52: 145500 | Q52: 145500 | R52: 2024-01-20 23:26:46.893096+00:00
A53: Alcove Homes | B53: FBE6JP8GIPM3 | C53: Thomas | D53: Sanchez | E53: 47300070688 | F53: Flats | G53: Occupied - Prepaid Water | H53: Block A, Apt. no. A6. Alcove Homes Estate 17-19 Ishola Street, Adekunle Yaba, Lagos | K53: Monthly Water Bill | L53: BILL | M53: SERVICE | N53: 45292 | O53: 45322 | P53: 10000 | Q53: 10000 | R53: 2024-01-20 23:26:46.893096+00:00
A54: Alcove Homes | B54: FB1308O6A2XM | C54: Lisa | D54: Clark | E54: 47300046662 | F54: Flats | G54: Occupied | H54: Block D, Apt. no. D6. Alcove Homes Estate 17-19 Ishola Street, Adekunle Yaba, Lagos | K54: Electricity Token - Any Amount | L54: BILL | M54: POWER | N54: 45292 | O54: 45322 | P54: 25000 | Q54: 25000 | R54: 2024-01-21 07:39:49.674580+00:00 | S54: 7305 9780 6052 2279 6368 | T54: 131.5
A55: Alcove Homes | B55: FB1308O6A2XM | C55: Lisa | D55: Clark | E55: 47300046662 | F55: Flats | G55: Occupied | H55: Block D, Apt. no. D6. Alcove Homes Estate 17-19 Ishola Street, Adekunle Yaba, Lagos | K55: Monthly Access Fee | L55: BILL | M55: SERVICE | N55: 45292 | O55: 45322 | P55: 500 | Q55: 500 | R55: 2024-01-21 07:39:49.674580+00:00
A56: Alcove Homes | B56: FBYZ912XK77R | C56: Jennifer | D56: Lewis | E56: 47300070845 | F56: Flats | G56: Occupied - Prepaid SC | H56: Block C, Apt. no. C2. Alcove Homes Estate 17-19 Ishola Street, Adekunle Yaba, Lagos | K56: Monthly Access Fee | L56: BILL | M56: SERVICE | N56: 45292 | O56: 45322 | P56: 500 | Q56: 500 | R56: 2024-01-22 10:27:06.826098+00:00
A57: Alcove Homes | B57: FBYZ912XK77R | C57: Michelle | D57: Wilson | E57: 47300070845 | F57: Flats | G57: Occupied - Prepaid SC | H57: Block C, Apt. no. C2. Alcove Homes Estate 17-19 Ishola Street, Adekunle Yaba, Lagos | K57: Monthly Water Bill | L57: BILL | M57: SERVICE | N57: 45292 | O57: 45322 | P57: 10000 | Q57: 10000 | R57: 2024-01-22 10:27:06.826098+00:00
A58: Alcove Homes | B58: FBEJOEQGC1DE | C58: Daniel | D58: Ramirez | E58: 47300046282 | F58: Flats | G58: Occupied - Prepaid Water | H58: Block A, Apt. no. A4. Alcove Homes Estate 17-19 Ishola Street, Adekunle Yaba, Lagos | K58: Monthly Water Bill | L58: BILL | M58: SERVICE | N58: 45292 | O58: 45322 | P58: 10000 | Q58: 10000 | R58: 2024-01-22 11:11:46.012950+00:00
A59: Alcove Homes | B59: FBI2JJ0HCI3O | C59: Jennifer | D59: Lewis | E59: 47300046399 | F59: Flats | G59: Occupied | H59: Block D, Apt. no. D3. Alcove Homes Estate 17-19 Ishola Street, Adekunle Yaba, Lagos | K59: Insurance Premium 2023/2024 Late payment penalty | L59: OUTSTANDING | N59: 45311 | O59: 45322 | P59: 2662.52 | Q59: 2662.52 | R59: 2024-01-22 11:23:35.879097+00:00
A60: Alcove Homes | B60: FB6OJ7XIRGW9 | C60: Michelle | D60: Wilson | E60: 47300070688 | F60: Flats | G60: Occupied - Prepaid Water | H60: Block A, Apt. no. A6. Alcove Homes Estate 17-19 Ishola Street, Adekunle Yaba, Lagos | K60: Monthly Water Bill | L60: BILL | M60: SERVICE | N60: 45292 | O60: 45322 | P60: 10000 | Q60: 10000 | R60: 2024-01-22 12:00:18.655784+00:00
A61: Alcove Homes | B61: FB43BB38TU47 | C61: Block_D | D61: Common_Area | E61: 47300070688 | F61: Flats | G61: Occupied - Prepaid Water | H61: Block A, Apt. no. A6. Alcove Homes Estate 17-19 Ishola Street, Adekunle Yaba, Lagos | K61: Extra Power Top Up - Any Amount | L61: BILL | M61: TOP_UP | P61: 80000 | Q61: 80000 | R61: 2024-01-22 12:01:55.696157+00:00 | S61: 2799 4969 5198 7972 7952 | T61: 421.1
A62: Alcove Homes | B62: FB6ZB3G8TGZR | C62: Patricia | D62: Williams | E62: 47300086445 | F62: Flats | G62: Occupied | H62: Block B, Apt. no. B5. Alcove Homes Estate 17-19 Ishola Street, Adekunle Yaba, Lagos | I62: Cranleigh Investment Limited | J62: House 5, 5th Avenue Gwarimpa Estate. Abuja FCT, Tel: 08145774497 | K62: Monthly Water Bill | L62: BILL | M62: SERVICE | N62: 45292 | O62: 45322 | P62: 10000 | Q62: 10000 | R62: 2024-01-22 12:40:05.538897+00:00
A63: Alcove Homes | B63: FB8AK0E96SU8 | C63: Susan | D63: Nguyen | E63: 47300086445 | F63: Flats | G63: Occupied | H63: Block B, Apt. no. B5. Alcove Homes Estate 17-19 Ishola Street, Adekunle Yaba, Lagos | I63: Cranleigh Investment Limited | J63: House 5, 5th Avenue Gwarimpa Estate. Abuja FCT, Tel: 08145774497 | K63: Extra Power Top Up - Any Amount | L63: BILL | M63: TOP_UP | P63: 27000 | Q63: 27000 | R63: 2024-01-22 12:41:54.355604+00:00 | S63: 2190 2709 4737 0282 5243 | T63: 142.1
A64: Alcove Homes | B64: FB337ACQJHB2 | C64: Donna | D64: Torres | E64: 47300025708 | F64: Office | G64: Office - No Water | H64: Block_D Common_Area | K64: Extra Power Top Up - Any Amount | L64: BILL | M64: TOP_UP | P64: 50000 | Q64: 50000 | R64: 2024-01-22 15:07:15.483655+00:00 | S64: 7180 5085 3182 0277 7981 | T64: 263.1
A65: Alcove Homes | B65: FB1V1X8433OF | C65: Jennifer | D65: Lewis | E65: 47300070522 | F65: Flats | G65: Occupied - Prepaid Water | H65: Block B, Apt. no. B8. Alcove Homes Estate 17-19 Ishola Street, Adekunle Yaba, Lagos | K65: Electricity Token - Any Amount | L65: BILL | M65: POWER | N65: 45292 | O65: 45322 | P65: 50000 | Q65: 50000 | R65: 2024-01-22 17:25:06.625588+00:00 | S65: 6156 5195 8111 0565 8648 | T65: 263.1
A66: Alcove Homes | B66: FB1V1X8433OF | C66: Jennifer | D66: Lewis | E66: 47300070522 | F66: Flats | G66: Occupied - Prepaid Water | H66: Block B, Apt. no. B8. Alcove Homes Estate 17-19 Ishola Street, Adekunle Yaba, Lagos | K66: Monthly Access Fee | L66: BILL | M66: SERVICE | N66: 45292 | O66: 45322 | P66: 500 | Q66: 500 | R66: 2024-01-22 17:25:06.625588+00:00
A67: Alcove Homes | B67: FB1V1X8433OF | C67: Michelle | D67: Wilson | E67: 47300070522 | F67: Flats | G67: Occupied - Prepaid Water | H67: Block B, Apt. no. B8. Alcove Homes Estate 17-19 Ishola Street, Adekunle Yaba, Lagos | K67: Monthly Water Bill | L67: BILL | M67: SERVICE | N67: 45292 | O67: 45322 | P67: 10000 | Q67: 10000 | R67: 2024-01-22 17:25:06.625588+00:00
A68: Alcove Homes | B68: FBNER5BBI78Q | C68: Patricia | D68: Williams | E68: 47300046779 | F68: Terrace | G68: Occupied | H68: Block I, Apt. no. I4. Alcove Homes Estate 17-19 Ishola Street, Adekunle Yaba, Lagos | K68: Electricity Token - Any Amount | L68: BILL | M68: POWER | N68: 45292 | O68: 45322 | P68: 100000 | Q68: 100000 | R68: 2024-01-22 23:33:43.303811+00:00 | S68: 5492 8796 5415 4321 2214 | T68: 526.3
A69: Alcove Homes | B69: FBNER5BBI78Q | C69: Susan | D69: Nguyen | E69: 47300046779 | F69: Terrace | G69: Occupied | H69: Block I, Apt. no. I4. Alcove Homes Estate 17-19 Ishola Street, Adekunle Yaba, Lagos | K69: Monthly Access Fee | L69: BILL | M69: SERVICE | N69: 45292 | O69: 45322 | P69: 500 | Q69: 500 | R69: 2024-01-22 23:33:43.303811+00:00
A70: Alcove Homes | B70: FBNER5BBI78Q | C70: Apartment | D70: A4 | E70: 47300046779 | F70: Terrace | G70: Occupied | H70: Block I, Apt. no. I4. Alcove Homes Estate 17-19 Ishola Street, Adekunle Yaba, Lagos | K70: Monthly Service Charge | L70: BILL | M70: SERVICE | N70: 45292 | O70: 45322 | P70: 145500 | Q70: 145500 | R70: 2024-01-22 23:33:43.303811+00:00
A71: Alcove Homes | B71: FBNER5BBI78Q | C71: Daniel | D71: Ramirez | E71: 47300046779 | F71: Terrace | G71: Occupied | H71: Block I, Apt. no. I4. Alcove Homes Estate 17-19 Ishola Street, Adekunle Yaba, Lagos | K71: Monthly Water Bill | L71: BILL | M71: SERVICE | N71: 45292 | O71: 45322 | P71: 10000 | Q71: 10000 | R71: 2024-01-22 23:33:43.303811+00:00
A72: Alcove Homes | B72: FB9VLFFLSFRY | C72: Massionette | D72: Area | E72: 47300070605 | F72: Flats | G72: Occupied | H72: Block B, Apt. no. B7. Alcove Homes Estate 17-19 Ishola Street, Adekunle Yaba, Lagos | K72: Electricity Token - Any Amount | L72: BILL | M72: POWER | N72: 45292 | O72: 45322 | P72: 20000 | Q72: 20000 | R72: 2024-01-23 07:45:17.136364+00:00 | S72: 5369 8044 3389 0655 9327 | T72: 105.2 | X72: Construction
A73: Alcove Homes | B73: FB9VLFFLSFRY | C73: Barbara | D73: Ramirez | E73: 47300070605 | F73: Flats | G73: Occupied | H73: Block B, Apt. no. B7. Alcove Homes Estate 17-19 Ishola Street, Adekunle Yaba, Lagos | K73: Monthly Access Fee | L73: BILL | M73: SERVICE | N73: 45292 | O73: 45322 | P73: 500 | Q73: 500 | R73: 2024-01-23 07:45:17.136364+00:00
A74: Alcove Homes | B74: FB9VLFFLSFRY | C74: Mark | D74: Rodriguez | E74: 47300070605 | F74: Flats | G74: Occupied | H74: Block B, Apt. no. B7. Alcove Homes Estate 17-19 Ishola Street, Adekunle Yaba, Lagos | K74: Monthly Service Charge | L74: BILL | M74: SERVICE | N74: 45292 | O74: 45322 | P74: 145500 | Q74: 145500 | R74: 2024-01-23 07:45:17.136364+00:00
A75: Alcove Homes | B75: FB9VLFFLSFRY | C75: Massionette | D75: Area | E75: 47300070605 | F75: Flats | G75: Occupied | H75: Block B, Apt. no. B7. Alcove Homes Estate 17-19 Ishola Street, Adekunle Yaba, Lagos | K75: Monthly Water Bill | L75: BILL | M75: SERVICE | N75: 45292 | O75: 45322 | P75: 10000 | Q75: 10000 | R75: 2024-01-23 07:45:17.136364+00:00 | X75: Construction
A76: Alcove Homes | B76: FB9HVR7MHQRD | C76: Barbara | D76: Ramirez | E76: 47300070654 | F76: Flats | G76: Occupied | H76: Block A, Apt. no. A7. Alcove Homes Estate 17-19 Ishola Street, Adekunle Yaba, Lagos | K76: Electricity Token - Any Amount | L76: BILL | M76: POWER | N76: 45292 | O76: 45322 | P76: 20000 | Q76: 20000 | R76: 2024-01-23 07:55:33.114102+00:00 | S76: 6804 2895 6322 8916 8625 | T76: 105.2
A77: Alcove Homes | B77: FB9HVR7MHQRD | C77: Mark | D77: Rodriguez | E77: 47300070654 | F77: Flats | G77: Occupied | H77: Block A, Apt. no. A7. Alcove Homes Estate 17-19 Ishola Street, Adekunle Yaba, Lagos | K77: Monthly Access Fee | L77: BILL | M77: SERVICE | N77: 45292 | O77: 45322 | P77: 500 | Q77: 500 | R77: 2024-01-23 07:55:33.114102+00:00
A78: Alcove Homes | B78: FBJOV7170FY4 | C78: MANAGMENT | D78: OFFICE | E78: 47300088367 | F78: Office | G78: Office - No Water | H78: Massionette Area - Construction | K78: Electricity Token - Any Amount | L78: BILL | M78: POWER | N78: 45292 | O78: 45322 | P78: 13000 | Q78: 13000 | R78: 2024-01-23 09:15:50.743568+00:00 | S78: 0952 2967 1478 0459 4775 | T78: 68.5
A79: Alcove Homes | B79: FBJOV7170FY4 | C79: Mark | D79: Rodriguez | E79: 47300088367 | F79: Office | G79: Office - No Water | H79: Massionette Area - Construction | K79: Monthly Access Fee | L79: BILL | M79: SERVICE | N79: 45292 | O79: 45322 | P79: 500 | Q79: 500 | R79: 2024-01-23 09:15:50.743568+00:00
A80: Alcove Homes | B80: FBTZW5W6QOSG | C80: Mark | D80: Rodriguez | E80: 47300070555 | F80: Office | G80: Office | H80: MANAGEMENT OFFICE | K80: Extra Power Top Up - Any Amount | L80: BILL | M80: TOP_UP | P80: 20000 | Q80: 20000 | R80: 2024-01-23 13:32:45.217845+00:00 | S80: 0469 7848 0575 4425 3881 | T80: 105.3
A81: Alcove Homes | B81: FBYXQYOL91YD | C81: Emily | D81: Thomas | E81: 47300046688 | F81: Flats | G81: Occupied - Prepaid Water | H81: Block C, Apt. no. C6. Alcove Homes Estate 17-19 Ishola Street, Adekunle Yaba, Lagos | K81: Electricity Token - Any Amount | L81: BILL | M81: POWER | N81: 45292 | O81: 45322 | P81: 20000 | Q81: 20000 | R81: 2024-01-24 14:00:50.972831+00:00 | S81: 1342 4077 6486 5367 8413 | T81: 105.2
A82: Alcove Homes | B82: FBYXQYOL91YD | C82: Emily | D82: Thomas | E82: 47300046688 | F82: Flats | G82: Occupied - Prepaid Water | H82: Block C, Apt. no. C6. Alcove Homes Estate 17-19 Ishola Street, Adekunle Yaba, Lagos | K82: Monthly Access Fee | L82: BILL | M82: SERVICE | N82: 45292 | O82: 45322 | P82: 500 | Q82: 500 | R82: 2024-01-24 14:00:50.972831+00:00
A83: Alcove Homes | B83: FBSN4VE4H39H | C83: Anthony | D83: Robinson | E83: 47300046720 | F83: Flats | G83: Occupied | H83: Block D, Apt. no. D2. Alcove Homes Estate 17-19 Ishola Street, Adekunle Yaba, Lagos | K83: Monthly Water Bill | L83: BILL | M83: SERVICE | N83: 45292 | O83: 45322 | P83: 10000 | Q83: 10000 | R83: 2024-01-24 20:31:38.477307+00:00
A84: Alcove Homes | B84: FBG4MWEXADFN | C84: Daniel | D84: Torres | E84: 47300070597 | F84: Flats | G84: Occupied | H84: Block A, Apt. no. A1. Alcove Homes Estate 17-19 Ishola Street, Adekunle Yaba, Lagos | K84: Electricity Token - Any Amount | L84: BILL | M84: POWER | N84: 45292 | O84: 45322 | P84: 40000 | Q84: 40000 | R84: 2024-01-25 08:50:56+00:00 | S84: 0084 6567 4306 5080 1735 | T84: 210.5
A85: Alcove Homes | B85: FBG4MWEXADFN | C85: Daniel | D85: Torres | E85: 47300070597 | F85: Flats | G85: Occupied | H85: Block A, Apt. no. A1. Alcove Homes Estate 17-19 Ishola Street, Adekunle Yaba, Lagos | K85: Monthly Access Fee | L85: BILL | M85: SERVICE | N85: 45292 | O85: 45322 | P85: 500 | Q85: 500 | R85: 2024-01-25 08:50:56+00:00
A86: Alcove Homes | B86: FBG4MWEXADFN | C86: Daniel | D86: Torres | E86: 47300070597 | F86: Flats | G86: Occupied | H86: Block A, Apt. no. A1. Alcove Homes Estate 17-19 Ishola Street, Adekunle Yaba, Lagos | K86: Monthly Service Charge | L86: BILL | M86: SERVICE | N86: 45292 | O86: 45322 | P86: 145500 | Q86: 145500 | R86: 2024-01-25 08:50:56+00:00
A87: Alcove Homes | B87: FBG4MWEXADFN | C87: Daniel | D87: Torres | E87: 47300070597 | F87: Flats | G87: Occupied | H87: Block A, Apt. no. A1. Alcove Homes Estate 17-19 Ishola Street, Adekunle Yaba, Lagos | K87: Monthly Water Bill | L87: BILL | M87: SERVICE | N87: 45292 | O87: 45322 | P87: 10000 | Q87: 10000 | R87: 2024-01-25 08:50:56+00:00
A88: Alcove Homes | B88: FBDU9VGX241K | C88: Anthony | D88: Lopez | E88: 47300070589 | F88: Flats | G88: Occupied | H88: Block B, Apt. no. B6. Alcove Homes Estate 17-19 Ishola Street, Adekunle Yaba, Lagos | K88: 2023 Sinking Fund + Penalty | L88: OUTSTANDING | N88: 45292 | O88: 45322 | P88: 113000 | Q88: 113000 | R88: 2024-01-26 18:45:00+00:00
A89: Alcove Homes | B89: FBDU9VGX241K | C89: Anthony | D89: Lopez | E89: 47300070589 | F89: Flats | G89: Occupied | H89: Block B, Apt. no. B6. Alcove Homes Estate 17-19 Ishola Street, Adekunle Yaba, Lagos | K89: Electricity Token - Any Amount | L89: BILL | M89: POWER | N89: 45292 | O89: 45322 | P89: 60000 | Q89: 60000 | R89: 2024-01-26 18:45:00+00:00 | S89: 0419 3603 7540 1681 7345 | T89: 315.7
A90: Alcove Homes | B90: FBDU9VGX241K | C90: Anthony | D90: Lopez | E90: 47300070589 | F90: Flats | G90: Occupied | H90: Block B, Apt. no. B6. Alcove Homes Estate 17-19 Ishola Street, Adekunle Yaba, Lagos | K90: Insurance Premium 2022/2023 late payment penalty | L90: OUTSTANDING | N90: 45311 | O90: 45322 | P90: 7013.73 | Q90: 7013.73 | R90: 2024-01-26 18:45:00+00:00
A91: Alcove Homes | B91: FBDU9VGX241K | C91: Anthony | D91: Lopez | E91: 47300070589 | F91: Flats | G91: Occupied | H91: Block B, Apt. no. B6. Alcove Homes Estate 17-19 Ishola Street, Adekunle Yaba, Lagos | K91: Monthly Access Fee | L91: BILL | M91: SERVICE | N91: 45292 | O91: 45322 | P91: 500 | Q91: 500 | R91: 2024-01-26 18:45:00+00:00
A92: Alcove Homes | B92: FBDU9VGX241K | C92: Anthony | D92: Lopez | E92: 47300070589 | F92: Flats | G92: Occupied | H92: Block B, Apt. no. B6. Alcove Homes Estate 17-19 Ishola Street, Adekunle Yaba, Lagos | K92: Monthly Service Charge | L92: BILL | M92: SERVICE | N92: 45292 | O92: 45322 | P92: 145500 | Q92: 145500 | R92: 2024-01-26 18:45:00+00:00
A93: Alcove Homes | B93: FBDU9VGX241K | C93: Anthony | D93: Lopez | E93: 47300070589 | F93: Flats | G93: Occupied | H93: Block B, Apt. no. B6. Alcove Homes Estate 17-19 Ishola Street, Adekunle Yaba, Lagos | K93: Monthly Water Bill | L93: BILL | M93: SERVICE | N93: 45292 | O93: 45322 | P93: 10000 | Q93: 10000 | R93: 2024-01-26 18:45:00+00:00
A94: Alcove Homes | B94: FB6ETSFWP2AU | C94: Thomas | D94: Sanchez | E94: 47300046241 | F94: Flats | G94: Occupied - Prepaid SC | H94: Block C, Apt. no. C5. Alcove Homes Estate 17-19 Ishola Street, Adekunle Yaba, Lagos | I94: Dr. Ibikunle Koya | J94: 0 | K94: Electricity Token - Any Amount | L94: BILL | M94: POWER | N94: 45292 | O94: 45322 | P94: 10000 | Q94: 10000 | R94: 2024-01-27 08:57:14+00:00 | S94: 1109 6396 6553 7808 4574 | T94: 52.6
A95: Alcove Homes | B95: FB6ETSFWP2AU | C95: Paul | D95: Perez | E95: 47300046241 | F95: Flats | G95: Occupied - Prepaid SC | H95: Block C, Apt. no. C5. Alcove Homes Estate 17-19 Ishola Street, Adekunle Yaba, Lagos | I95: Dr. Ibikunle Koya | J95: 0 | K95: Monthly Access Fee | L95: BILL | M95: SERVICE | N95: 45292 | O95: 45322 | P95: 500 | Q95: 500 | R95: 2024-01-27 08:57:14+00:00
A96: Alcove Homes | B96: FB6ETSFWP2AU | C96: Thomas | D96: Sanchez | E96: 47300046241 | F96: Flats | G96: Occupied - Prepaid SC | H96: Block C, Apt. no. C5. Alcove Homes Estate 17-19 Ishola Street, Adekunle Yaba, Lagos | I96: Dr. Ibikunle Koya | J96: 0 | K96: Monthly Service Charge | L96: BILL | M96: SERVICE | N96: 45292 | O96: 45322 | P96: 145500 | Q96: 145500 | R96: 2024-01-27 08:57:14+00:00
A97: Alcove Homes | B97: FB6ETSFWP2AU | C97: Thomas | D97: Sanchez | E97: 47300046241 | F97: Flats | G97: Occupied - Prepaid SC | H97: Block C, Apt. no. C5. Alcove Homes Estate 17-19 Ishola Street, Adekunle Yaba, Lagos | I97: Dr. Ibikunle Koya | J97: 0 | K97: Monthly Water Bill | L97: BILL | M97: SERVICE | N97: 45292 | O97: 45322 | P97: 10000 | Q97: 10000 | R97: 2024-01-27 08:57:14+00:00
A98: Alcove Homes | B98: FB7V0WM6VCA8 | C98: Thomas | D98: Sanchez | E98: 47300046977 | F98: Flats | G98: Occupied - Prepaid Water | H98: Block D, Apt. no. D1. Alcove Homes Estate 17-19 Ishola Street, Adekunle Yaba, Lagos | K98: Electricity Token - Any Amount | L98: BILL | M98: POWER | N98: 45292 | O98: 45322 | P98: 80000 | Q98: 80000 | R98: 2024-01-27 22:21:31.927306+00:00 | S98: 0911 1672 2678 3836 3423 | T98: 421
A99: Alcove Homes | B99: FBA8K41BY8PL | C99: Betty | D99: Lopez | E99: 47300070753 | F99: Flats | G99: Occupied - Prepaid Water | H99: Block A, Apt. no. A2. Alcove Homes Estate 17-19 Ishola Street, Adekunle Yaba, Lagos | K99: Monthly Access Fee | L99: BILL | M99: SERVICE | N99: 45292 | O99: 45322 | P99: 500 | Q99: 500 | R99: 2024-01-28 11:41:05.184364+00:00
A100: Alcove Homes | B100: FBURSRGX8Q4X | C100: Block | D100: C_Common_Area | E100: 47300070555 | F100: Office | G100: Office | H100: MANAGEMENT OFFICE | K100: Extra Power Top Up - Any Amount | L100: BILL | M100: TOP_UP | P100: 20000 | Q100: 20000 | R100: 2024-01-29 09:15:43.549395+00:00 | S100: 4410 2521 6435 3533 3861 | T100: 105.2
...

Sheet Cleaned Data
A1: ESTATE FINANCIAL TRANSACTIONS FOR THE PERIOD OF JANUARY - DECEMBER 2024
M2: Progress | O2: =COUNTIF(O5:O13, TRUE)/COUNTA(O5:O13) -> 1
A3: Order ID | B3: Full Name | C3: Unit Type | D3: Block | E3: Apartment ID | F3: Bill | G3: Date | H3: Token | I3: Unit | J3: Unit Price | K3: Total Price
A4: FBFCDK7M98DQ | B4: Barbara Martinez | C4: Flats | D4: Block C | E4: C3 | F4: Access Fee | G4: 45307 | H4: 0 | I4: 0 | J4: 500 | K4: 500 | M4: LOOKUP!!!
A5: FBSQ2CO2IRP2 | B5: Power House Common Area Area | C5: Office | D5: Power House | E5: Common Area | F5: Access Fee | G5: 45307 | H5: 0 | I5: 0 | J5: 500 | K5: 500 | L5: 1 | M5: Sum of All Service Bills For The Year | O5: TRUE
A6: FBIUG35BP7HT | B6: Patricia Williams | C6: Flats | D6: Block B | E6: B5 | F6: Access Fee | G6: 45307 | H6: 0 | I6: 0 | J6: 500 | K6: 500 | L6: 2 | M6: Sum of Electricity Recharge | O6: TRUE
A7: FBNCBJF57W9S | B7: Block D Common Area | C7: Office | D7: Block D | E7: Common Area | F7: Access Fee | G7: 45307 | H7: 0 | I7: 0 | J7: 500 | K7: 500 | L7: 3 | M7: Maximum Amount - Selected Service Bill | O7: TRUE
A8: FBW7CPUUH2I1 | B8: Williams Jef | C8: Flats | D8: Block A | E8: A4 | F8: Access Fee | G8: 45308 | H8: 0 | I8: 0 | J8: 500 | K8: 500 | L8: 4 | M8: Minimum Amount - Selected Service Bill | O8: TRUE
A9: FBJP8CYMRKX3 | B9: Andrew Allen | C9: Flats | D9: Block B | E9: B4 | F9: Access Fee | G9: 45308 | H9: 0 | I9: 0 | J9: 500 | K9: 500 | L9: 5 | M9: Sum of Service Charge | O9: TRUE
A10: FB0DAH5B58LU | B10: MANAGMENT Office | C10: Office | D10: Management | E10: Office | F10: Access Fee | G10: 45309 | H10: 0 | I10: 0 | J10: 500 | K10: 500 | L10: 6 | M10: Sum of Selected Service Bill by Apartment | O10: TRUE
A11: FBZWBY2OZT9F | B11: Richard Allen | C11: Flats | D11: Block B | E11: B2 | F11: Access Fee | G11: 45309 | H11: 0 | I11: 0 | J11: 500 | K11: 500 | L11: 7 | M11: Sum of all Apartment Service Bills | O11: TRUE
A12: FB1QUKZJEB98 | B12: Anthony Robinson | C12: Flats | D12: Block D | E12: D2 | F12: Access Fee | G12: 45310 | H12: 0 | I12: 0 | J12: 500 | K12: 500 | L12: 8 | M12: Use Pivot Tables to Present Useful Data | O12: TRUE
A13: FBJ4DDISRHYC | B13: Donna Torres | C13: Flats | D13: Block D | E13: D3 | F13: Access Fee | G13: 45310 | H13: 0 | I13: 0 | J13: 500 | K13: 500 | L13: 9 | M13: Use Charts to Visualize Service Bills | O13: TRUE
A14: FBO6H19ZP0LK | B14: Michael Wright | C14: Flats | D14: Block D | E14: D5 | F14: Access Fee | G14: 45310 | H14: 0 | I14: 0 | J14: 500 | K14: 500
A15: FBGPF8KEHF2M | B15: Donald Jones | C15: Flats | D15: Block C | E15: C4 | F15: Access Fee | G15: 45310 | H15: 0 | I15: 0 | J15: 500 | K15: 500 | M15: Sum of All Service Bills For The Year
A16: FBXBWICH8LAQ | B16: Paul Garcia | C16: Flats | D16: Block D | E16: D7 | F16: Access Fee | G16: 45310 | H16: 0 | I16: 0 | J16: 500 | K16: 500 | M16: Criteria | N16: Sum
A17: FBXUB8UT7Z61 | B17: Security Utilities Common Area | C17: Office | D17: Security Utilities | E17: Common Area | F17: Access Fee | G17: 45310 | H17: 0 | I17: 0 | J17: 500 | K17: 500 | M17: All Bills | N17: =SUM(Estate_bills[Total Price]) -> 1.4899739e+08
A18: FB0Y6MK1WKSR | B18: Joshua Harris | C18: Terrace | D18: Block I | E18: I1 | F18: Access Fee | G18: 45310 | H18: 0 | I18: 0 | J18: 500 | K18: 500
A19: FBCESN2HIEL9 | B19: Karen Rodriguez | C19: Terrace | D19: Block I | E19: I2 | F19: Access Fee | G19: 45310 | H19: 0 | I19: 0 | J19: 500 | K19: 500 | M19: Sum of Electricity Recharge
A20: FBE6JP8GIPM3 | B20: Susan Nguyen | C20: Flats | D20: Block D | E20: D6 | F20: Access Fee | G20: 45311 | H20: 0 | I20: 0 | J20: 500 | K20: 500 | M20: Criteria | N20: Sum
A21: FBEJZNM1SKLT | B21: Paul Torres | C21: Flats | D21: Block B | E21: B1 | F21: Access Fee | G21: 45311 | H21: 0 | I21: 0 | J21: 500 | K21: 500 | M21: Service charge | N21: =SUMIF(Estate_bills[Bill],M21,Estate_bills[Total Price]) -> 51883291
A22: FB3QW638HYG1 | B22: Paul Perez | C22: Flats | D22: Block D | E22: D1 | F22: Access Fee | G22: 45311 | H22: 0 | I22: 0 | J22: 500 | K22: 500
A23: FB1308O6A2XM | B23: Lisa Clark | C23: Flats | D23: Block D | E23: D6 | F23: Access Fee | G23: 45312 | H23: 0 | I23: 0 | J23: 500 | K23: 500 | M23: Maximum Amount - Selected Service Bill
A24: FBNER5BBI78Q | B24: Jennifer Lewis | C24: Terrace | D24: Block I | E24: I4 | F24: Access Fee | G24: 45313 | H24: 0 | I24: 0 | J24: 500 | K24: 500 | M24: Criteria | N24: Sum
A25: FB1V1X8433OF | B25: Michelle Wilson | C25: Flats | D25: Block B | E25: B8 | F25: Access Fee | G25: 45313 | H25: 0 | I25: 0 | J25: 500 | K25: 500 | M25: Electricity Recharge | N25: =_xlfn.MAXIFS(Estate_bills[Total Price],Estate_bills[Bill],M25) -> 250000
A26: FBYZ912XK77R | B26: Daniel Ramirez | C26: Flats | D26: Block C | E26: C2 | F26: Access Fee | G26: 45313 | H26: 0 | I26: 0 | J26: 500 | K26: 500
A27: FBJOV7170FY4 | B27: Massionette Area Construction | C27: Office | D27: Massionette | E27: Construction | F27: Access Fee | G27: 45314 | H27: 0 | I27: 0 | J27: 500 | K27: 500 | M27: Minimum Amount - Selected Service Bill
A28: FB9HVR7MHQRD | B28: Barbara Ramirez | C28: Flats | D28: Block A | E28: A7 | F28: Access Fee | G28: 45314 | H28: 0 | I28: 0 | J28: 500 | K28: 500 | M28: Criteria | N28: Sum
A29: FB9VLFFLSFRY | B29: Mark Rodriguez | C29: Flats | D29: Block B | E29: B7 | F29: Access Fee | G29: 45314 | H29: 0 | I29: 0 | J29: 500 | K29: 500 | M29: Fixed Charge | N29: =_xlfn.MINIFS(Estate_bills[Total Price],Estate_bills[Bill],M29) -> 33222.01
A30: FBYXQYOL91YD | B30: Emily Thomas | C30: Flats | D30: Block C | E30: C6 | F30: Access Fee | G30: 45315 | H30: 0 | I30: 0 | J30: 500 | K30: 500
A31: FBG4MWEXADFN | B31: Daniel Torres | C31: Flats | D31: Block A | E31: A1 | F31: Access Fee | G31: 45316 | H31: 0 | I31: 0 | J31: 500 | K31: 500 | M31: Sum of Service Charge
A32: FBDU9VGX241K | B32: Anthony Lopez | C32: Flats | D32: Block B | E32: B6 | F32: Access Fee | G32: 45317 | H32: 0 | I32: 0 | J32: 500 | K32: 500 | M32: Criteria | N32: Sum
A33: FB6ETSFWP2AU | B33: Thomas Sanchez | C33: Flats | D33: Block C | E33: C5 | F33: Access Fee | G33: 45318 | H33: 0 | I33: 0 | J33: 500 | K33: 500 | M33: Service Charge | N33: =SUMIF(Estate_bills[Bill],M33,Estate_bills[Total Price]) -> 51883291
A34: FBA8K41BY8PL | B34: Betty Lopez | C34: Flats | D34: Block A | E34: A2 | F34: Access Fee | G34: 45319 | H34: 0 | I34: 0 | J34: 500 | K34: 500
A35: FBTJURBASI3K | B35: Block C Common Area | C35: Office | D35: Block C | E35: Common Area | F35: Access Fee | G35: 45320 | H35: 0 | I35: 0 | J35: 500 | K35: 500 | M35: Sum of Selected Service Bill by Apartment
A36: FBEPQXHWWHRV | B36: Karen Allen | C36: Pent House | D36: Block D | E36: DPH | F36: Access Fee | G36: 45320 | H36: 0 | I36: 0 | J36: 500 | K36: 500 | M36: Criteria | N36: Apartment ID | O36: Sum
A37: FB5F4YTQF28S | B37: Terrace Area Construction | C37: Office | D37: Terrace | E37: Construction | F37: Access Fee | G37: 45321 | H37: 0 | I37: 0 | J37: 500 | K37: 500 | M37: Fixed charge | N37: C3 | O37: =SUMIFS(Estate_bills[Total Price],Estate_bills[Bill],M37,Estate_bills[Apartment ID],N37) -> 250376.4
A38: FB7A303OZ7FZ | B38: Elizabeth Martin | C38: Flats | D38: Block A | E38: A8 | F38: Access Fee | G38: 45322 | H38: 0 | I38: 0 | J38: 500 | K38: 6000
A39: FBWHEE3PU981 | B39: Robert Robinson | C39: Flats | D39: Block C | E39: C7 | F39: Access Fee | G39: 45322 | H39: 0 | I39: 0 | J39: 500 | K39: 500
A40: FBUMD2OWD0AX | B40: Nancy Sanchez | C40: Pent House | D40: Block A | E40: APH | F40: Access Fee | G40: 45322 | H40: 0 | I40: 0 | J40: 500 | K40: 500 | M40: Sum of all Apartment Service Bills
A41: FBIUZ0QZQS8Z | B41: Donald Jones | C41: Flats | D41: Block C | E41: C4 | F41: Access Fee | G41: 45323 | H41: 0 | I41: 0 | J41: 500 | K41: 500 | M41: Apartment ID
A42: FB4LLM6IN50W | B42: Daniel Ramirez | C42: Flats | D42: Block C | E42: C2 | F42: Access Fee | G42: 45323 | H42: 0 | I42: 0 | J42: 500 | K42: 500 | M42: D6
A43: FBRHSIJ8P0XY | B43: Michael Wright | C43: Flats | D43: Block D | E43: D5 | F43: Access Fee | G43: 45323 | H43: 0 | I43: 0 | J43: 500 | K43: 500 | M43: Criteria (All Bills) | N43: Sum
A44: FBHMTSH4ED57 | B44: Patricia Williams | C44: Flats | D44: Block B | E44: B5 | F44: Access Fee | G44: 45323 | H44: 0 | I44: 0 | J44: 500 | K44: 500 | M44: Service Charge | N44: =SUMIFS(Estate_bills[Total Price],Estate_bills[Apartment ID],$M$42,Estate_bills[Bill],M44) -> 3061546.5
A45: FBTESEBCGNPJ | B45: Paul Garcia | C45: Flats | D45: Block D | E45: D7 | F45: Access Fee | G45: 45323 | H45: 0 | I45: 0 | J45: 500 | K45: 500 | M45: Electricity Recharge | N45: =SUMIFS(Estate_bills[Total Price],Estate_bills[Apartment ID],$M$42,Estate_bills[Bill],M45) -> 2003300
A46: FB52CLMO075Q | B46: Mary Hernandez | C46: Flats | D46: Block C | E46: C8 | F46: Access Fee | G46: 45323 | H46: 0 | I46: 0 | J46: 500 | K46: 500 | M46: Fixed Charge | N46: =SUMIFS(Estate_bills[Total Price],Estate_bills[Apartment ID],$M$42,Estate_bills[Bill],M46) -> 752660.82
A47: FBVZQMDX5UPP | B47: Robert Robinson | C47: Flats | D47: Block C | E47: C7 | F47: Access Fee | G47: 45324 | H47: 0 | I47: 0 | J47: 500 | K47: 500 | M47: Access Fee | N47: =SUMIFS(Estate_bills[Total Price],Estate_bills[Apartment ID],$M$42,Estate_bills[Bill],M47) -> 12000
A48: FBCQW66XXOCX | B48: Thomas Sanchez | C48: Flats | D48: Block C | E48: C5 | F48: Access Fee | G48: 45324 | H48: 0 | I48: 0 | J48: 500 | K48: 500 | M48: Water Bill | N48: =SUMIFS(Estate_bills[Total Price],Estate_bills[Apartment ID],$M$42,Estate_bills[Bill],M48) -> 260000
A49: FBE37RT5S25O | B49: Joshua Harris | C49: Terrace | D49: Block I | E49: I1 | F49: Access Fee | G49: 45325 | H49: 0 | I49: 0 | J49: 500 | K49: 500 | M49: Insurance Premium | N49: =SUMIFS(Estate_bills[Total Price],Estate_bills[Apartment ID],$M$42,Estate_bills[Bill],M49) -> 82173.58
A50: FBNQIOQ9QP9S | B50: Williams Jef | C50: Flats | D50: Block A | E50: A4 | F50: Access Fee | G50: 45325 | H50: 0 | I50: 0 | J50: 500 | K50: 500 | M50: Sinking Fund | N50: =SUMIFS(Estate_bills[Total Price],Estate_bills[Apartment ID],$M$42,Estate_bills[Bill],M50) -> 0
A51: FB5BCVT9XXW4 | B51: Block D Common Area | C51: Office | D51: Block D | E51: Common Area | F51: Access Fee | G51: 45325 | H51: 0 | I51: 0 | J51: 500 | K51: 500 | M51: Insurance Premium Late Payment Charge | N51: =SUMIFS(Estate_bills[Total Price],Estate_bills[Apartment ID],$M$42,Estate_bills[Bill],M51) -> 8217.36
A52: FBL4SIVPQWQC | B52: Power House Common Area Area | C52: Office | D52: Power House | E52: Common Area | F52: Access Fee | G52: 45325 | H52: 0 | I52: 0 | J52: 500 | K52: 500 | M52: Obstruction Infraction | N52: =SUMIFS(Estate_bills[Total Price],Estate_bills[Apartment ID],$M$42,Estate_bills[Bill],M52) -> 0
A53: FB9DT5AIXWFK | B53: MANAGMENT Office | C53: Office | D53: Management | E53: Office | F53: Access Fee | G53: 45325 | H53: 0 | I53: 0 | J53: 500 | K53: 500 | M53: Parking Infraction | N53: =SUMIFS(Estate_bills[Total Price],Estate_bills[Apartment ID],$M$42,Estate_bills[Bill],M53) -> 0
A54: FBOTEONCR45D | B54: Anthony Robinson | C54: Flats | D54: Block D | E54: D2 | F54: Access Fee | G54: 45326 | H54: 0 | I54: 0 | J54: 500 | K54: 500 | M54: Water Bill Late Payment Charge | N54: =SUMIFS(Estate_bills[Total Price],Estate_bills[Apartment ID],$M$42,Estate_bills[Bill],M54) -> 0
A55: FBRCYSLZJ8CJ | B55: Barbara Ramirez | C55: Flats | D55: Block A | E55: A7 | F55: Access Fee | G55: 45327 | H55: 0 | I55: 0 | J55: 500 | K55: 500 | M55: Total | N55: =SUM(N44:N54) -> 6179898.2
A56: FBW8PGI9UEMB | B56: Richard Allen | C56: Flats | D56: Block B | E56: B2 | F56: Access Fee | G56: 45327 | H56: 0 | I56: 0 | J56: 500 | K56: 500
A57: FBT9YEH2225M | B57: Michelle Wilson | C57: Flats | D57: Block B | E57: B8 | F57: Access Fee | G57: 45327 | H57: 0 | I57: 0 | J57: 500 | K57: 500
A58: FBX3F5VQMKMX | B58: Daniel Torres | C58: Flats | D58: Block A | E58: A1 | F58: Access Fee | G58: 45328 | H58: 0 | I58: 0 | J58: 500 | K58: 500
A59: FBRSCDCRE0Y2 | B59: James Clark | C59: Flats | D59: Block A | E59: A5 | F59: Access Fee | G59: 45328 | H59: 0 | I59: 0 | J59: 500 | K59: 500
A60: FBMEXNHOY1SB | B60: Security Utilities Common Area | C60: Office | D60: Security Utilities | E60: Common Area | F60: Access Fee | G60: 45330 | H60: 0 | I60: 0 | J60: 500 | K60: 500
A61: FB3A3YSXGERK | B61: Karen Rodriguez | C61: Terrace | D61: Block I | E61: I2 | F61: Access Fee | G61: 45330 | H61: 0 | I61: 0 | J61: 500 | K61: 500
A62: FBCCV4YZO149 | B62: Karen Allen | C62: Pent House | D62: Block D | E62: DPH | F62: Access Fee | G62: 45331 | H62: 0 | I62: 0 | J62: 500 | K62: 500
A63: FBZIETG0ZGB5 | B63: Massionette Area Construction | C63: Office | D63: Massionette | E63: Construction | F63: Access Fee | G63: 45331 | H63: 0 | I63: 0 | J63: 500 | K63: 500
A64: FB0AD5L4SAJ1 | B64: Terrace Area Construction | C64: Office | D64: Terrace | E64: Construction | F64: Access Fee | G64: 45331 | H64: 0 | I64: 0 | J64: 500 | K64: 500
A65: FB0HBJJ9MNIT | B65: Sarah Wilson | C65: Flats | D65: Block D | E65: D4 | F65: Access Fee | G65: 45332 | H65: 0 | I65: 0 | J65: 500 | K65: 500
A66: FBBOJP13HJ1Z | B66: Lisa Clark | C66: Flats | D66: Block D | E66: D6 | F66: Access Fee | G66: 45333 | H66: 0 | I66: 0 | J66: 500 | K66: 500
A67: FBS0UD5SR9FT | B67: Emily Thomas | C67: Flats | D67: Block C | E67: C6 | F67: Access Fee | G67: 45333 | H67: 0 | I67: 0 | J67: 500 | K67: 500
... A506: FB5Q14S2YD8L | B506: Susan Nguyen | C506: Flats | D506: Block D | E506: D6 | F506: Access Fee | G506: 45646 | H506: 0 | I506: 0 | J506: 500 | K506: 500
A507: FB3V5J8PL5ED | B507: Donald Jones | C507: Flats | D507: Block C | E507: C4 | F507: Access Fee | G507: 45647 | H507: 0 | I507: 0 | J507: 500 | K507: 500 | L507: =COUNTBLANK(A504:I3015) -> 4517
A508: FBDL8AI9IFET | B508: Mary Hernandez | C508: Flats | D508: Block C | E508: C8 | F508: Access Fee | G508: 45649 | H508: 0 | I508: 0 | J508: 500 | K508: 500
A509: FB3W1UHYLE38 | B509: Mary Hernandez | C509: Flats | D509: Block C | E509: C8 | F509: Access Fee | G509: 45649 | H509: 0 | I509: 0 | J509: 500 | K509: 500
A510: FB3W1UHYLE38 | B510: Mary Hernandez | C510: Flats | D510: Block C | E510: C8 | F510: Access Fee | G510: 45649 | H510: 0 | I510: 0 | J510: 500 | K510: 500
A511: FBD0OG1Y2CQO | B511: Daniel Torres | C511: Flats | D511: Block A | E511: A1 | F511: Access Fee | G511: 45652 | H511: 0 | I511: 0 | J511: 500 | K511: 500
A512: FB2VDU78HREM | B512: Barbara Martinez | C512: Flats | D512: Block C | E512: C3 | F512: Ante room annual rental charge (March 2024 -February 2025) | G512: 45455 | H512: 0 | I512: 0 | J512: 100000 | K512: 100000
A513: FBX3IRC19APV | B513: MANAGMENT Office | C513: Office | D513: Management | E513: Office | F513: Electricity Recharge | G513: 45300 | H513: 4171 2599 1916 0300 1098 | I513: 1 | J513: 200 | K513: 200
A514: FBFCDK7M98DQ | B514: Barbara Martinez | C514: Flats | D514: Block C | E514: C3 | F514: Electricity Recharge | G514: 45307 | H514: 3446 6037 9260 8339 9302 | I514: 210.5 | J514: 40000 | K514: 40000
A515: FBSQ2CO2IRP2 | B515: Power House Common Area Area | C515: Office | D515: Power House | E515: Common Area | F515: Electricity Recharge | G515: 45307 | H515: 1481 9068 3005 1342 8693 | I515: 526.3 | J515: 100000 | K515: 100000
A516: FBIUG35BP7HT | B516: Patricia Williams | C516: Flats | D516: Block B | E516: B5 | F516: Electricity Recharge | G516: 45307 | H516: 1955 4821 7035 2914 4034 | I516: 131.5 | J516: 25000 | K516: 25000
A517: FBNCBJF57W9S | B517: Block D Common Area | C517: Office | D517: Block D | E517: Common Area | F517: Electricity Recharge | G517: 45307 | H517: 5765 5477 1290 4259 1775 | I517: 263 | J517: 50000 | K517: 50000
A518: FBJP8CYMRKX3 | B518: Andrew Allen | C518: Flats | D518: Block B | E518: B4 | F518: Electricity Recharge | G518: 45308 | H518: 1805 4045 6763 6696 1614 | I518: 394.7 | J518: 75000 | K518: 75000
A519: FBZWBY2OZT9F | B519: Richard Allen | C519: Flats | D519: Block B | E519: B2 | F519: Electricity Recharge | G519: 45309 | H519: 1171 5286 4173 3400 5280 | I519: 421 | J519: 80000 | K519: 80000
A520: FB83EPZM5BGF | B520: MANAGMENT Office | C520: Office | D520: Management | E520: Office | F520: Electricity Recharge | G520: 45309 | H520: 1502 5537 3637 7452 5280 | I520: 105.3 | J520: 20000 | K520: 20000
A521: FB1QUKZJEB98 | B521: Anthony Robinson | C521: Flats | D521: Block D | E521: D2 | F521: Electricity Recharge | G521: 45310 | H521: 3526 9927 4664 2030 5627 | I521: 131.5 | J521: 25000 | K521: 25000
A522: FBJ4DDISRHYC | B522: Donna Torres | C522: Flats | D522: Block D | E522: D3 | F522: Electricity Recharge | G522: 45310 | H522: 3822 0525 9297 6342 0056 | I522: 105.2 | J522: 20000 | K522: 20000
A523: FBGPF8KEHF2M | B523: Donald Jones | C523: Flats | D523: Block C | E523: C4 | F523: Electricity Recharge | G523: 45310 | H523: 5981 7617 3889 5751 9629 | I523: 263.1 | J523: 50000 | K523: 50000
A524: FB20FQAKV9UI | B524: Paul Garcia | C524: Flats | D524: Block D | E524: D7 | F524: Electricity Recharge | G524: 45310 | H524: 6747 8832 0668 6589 1351 | I524: 473.6 | J524: 90000 | K524: 90000
... A1645: FBCK129LOTBT | B1645: Power House Common Area Area | C1645: Office | D1645: Power House | E1645: Common Area | F1645: Electricity Recharge | G1645: 45657 | H1645: 2777 7618 0543 4178 2904 | I1645: 416.3 | J1645: 100000 | K1645: 100000
A1646: FB5JR2VYHA6N | B1646: Michelle Wilson | C1646: Flats | D1646: Block B | E1646: B8 | F1646: Fixed Charge | G1646: 45541 | H1646: 0 | I1646: 0 | J1646: 64912.4 | K1646: 64912.4
A1647: FB92B0LCJS9J | B1647: Sarah Wilson | C1647: Flats | D1647: Block D | E1647: D4 | F1647: Fixed Charge | G1647: 45541 | H1647: 0 | I1647: 0 | J1647: 64912.4 | K1647: 64912.4
A1648: FBRF9NK4VW4M | B1648: Jennifer Robinson | C1648: Terrace | D1648: Block I | E1648: I3 | F1648: Fixed Charge | G1648: 45541 | H1648: 0 | I1648: 0 | J1648: 64912.4 | K1648: 64912.4
A1649: FBM74DJ58RQ0 | B1649: Paul Garcia | C1649: Flats | D1649: Block D | E1649: D7 | F1649: Fixed Charge | G1649: 45541 | H1649: 0 | I1649: 0 | J1649: 64912.4 | K1649: 64912.4
A1650: FBQBLP6P4KWQ | B1650: Robert Walker | C1650: Flats | D1650: Block B | E1650: B3 | F1650: Fixed Charge | G1650: 45541 | H1650: 0 | I1650: 0 | J1650: 64912.4 | K1650: 64912.4
A1651: FB3YP4RDCLAG | B1651: Anthony Robinson | C1651: Flats | D1651: Block D | E1651: D2 | F1651: Fixed Charge | G1651: 45541 | H1651: 0 | I1651: 0 | J1651: 64912.4 | K1651: 64912.4
A1652: FBX0FJEV2WBN | B1652: Betty Lopez | C1652: Flats | D1652: Block A | E1652: A2 | F1652: Fixed Charge | G1652: 45541 | H1652: 0 | I1652: 0 | J1652: 64912.4 | K1652: 64912.4
A1653: FBZ5LJJJ976E | B1653: Jennifer Lewis | C1653: Terrace | D1653: Block I | E1653: I4 | F1653: Fixed Charge | G1653: 45541 | H1653: 0 | I1653: 0 | J1653: 64912.4 | K1653: 64912.4
A1654: FBOAUMMVPG9F | B1654: Emily Thomas | C1654: Flats | D1654: Block C | E1654: C6 | F1654: Fixed Charge | G1654: 45541 | H1654: 0 | I1654: 0 | J1654: 64912.4 | K1654: 64912.4
A1655: FBD5IJ2J6RMT | B1655: Donald Jones | C1655: Flats | D1655: Block C | E1655: C4 | F1655: Fixed Charge | G1655: 45541 | H1655: 0 | I1655: 0 | J1655: 64912.4 | K1655: 64912.4
A1656: FBL9E72EZJIZ | B1656: Donna Torres | C1656: Flats | D1656: Block D | E1656: D3 | F1656: Fixed Charge | G1656: 45541 | H1656: 0 | I1656: 0 | J1656: 64912.4 | K1656: 64912.4
A1657: FB8XK6WH3S9B | B1657: Karen Rodriguez | C1657: Terrace | D1657: Block I | E1657: I2 | F1657: Fixed Charge | G1657: 45541 | H1657: 0 | I1657: 0 | J1657: 64912.4 | K1657: 64912.4
... A2513: FBM7AEDLM7HK | B2513: Barbara Martinez | C2513: Flats | D2513: Block C | E2513: C3 | F2513: Water Bill Late Payment Charge | G2513: 45322 | H2513: 0 | I2513: 0 | J2513: 4750 | K2513: 4750
...

Sheet Pivot Tables
X7: Bill | Y7: (All)
A9: Row Labels | B9: Sum of All Service Bills | D9: Electricity Recharge | E9: Column Labels | G9: Service Charge | H9: Column Labels | J9: Fixed Charge | K9: Column Labels | M9: Water Bill | N9: Column Labels | Q9: Access Fee | R9: Column Labels | T9: Power Recharge & Water Bill by the Office & Common Area | U9: Column Labels | X9: Row Labels | Y9: Sum
A10: Office | B10: 1096200 | D10: Row Labels | E10: Electricity Recharge | G10: Row Labels | H10: Service Charge | J10: Row Labels | K10: Fixed Charge | M10: Row Labels | N10: Water Bill | O10: Water Bill Late Payment Charge | Q10: Row Labels | R10: Fixed Charge | T10: Row Labels | U10: Electricity Recharge | V10: Water Bill | X10: D6 | Y10: 6655261
A11: I4 | B11: 3350643.5 | D11: A1 | E11: 517500 | G11: A1 | H11: 1870574.9 | J11: A1 | K11: 376330.41 | M11: A1 | N11: 120000 | Q11: A1 | R11: 376330.41 | T11: Common Area | U11: 22092500 | V11: 10000 | X11: I2 | Y11: 5281444
A12: I3 | B12: 3041775.8 | D12: A2 | E12: 932000 | G12: A2 | H12: 602600 | J12: A2 | K12: 376330.41 | M12: A2 | N12: 90000 | Q12: A2 | R12: 376330.41 | T12: Office | U12: 1090200 | X12: I1 | Y12: 5280471.8
A13: I2 | B13: 5281444 | D13: A3 | E13: 510809.49 | G13: A3 | H13: 873000 | J13: A3 | K13: 64912.4 | M13: A3 | N13: 90000 | Q13: A3 | R13: 64912.4 | T13: Grand Total | U13: 23182700 | V13: 10000 | X13: A8 | Y13: 4793920.7
A14: I1 | B14: 5280471.8 | D14: A4 | E14: 500000 | G14: A5 | H14: 1324950 | J14: A4 | K14: 64912.4 | M14: A4 | N14: 130000 | Q14: A4 | R14: 64912.4 | X14: C3 | Y14: 4724412.5
A15: DPH | B15: 4297111.8 | D15: A5 | E15: 260000 | G15: A7 | H15: 1039100 | J15: A5 | K15: 250376.4 | M15: A5 | N15: 80000 | Q15: A5 | R15: 250376.4 | X15: B5 | Y15: 4502033.3
A16: D8 | B16: 2924762.9 | D16: A7 | E16: 638000 | G16: A8 | H16: 713908.86 | J16: A7 | K16: 376330.41 | M16: A7 | N16: 40000 | Q16: A7 | R16: 376330.41 | X16: C4 | Y16: 4427955
A17: D7 | B17: 3383466.9 | D17: A8 | E17: 3450000 | G17: APH | H17: 1324950 | J17: A8 | K17: 376330.41 | M17: A8 | N17: 10000 | Q17: A8 | R17: 376330.41 | X17: DPH | Y17: 4297111.8
A18: D6 | B18: 6655261 | D18: APH | E18: 1230000 | G18: B1 | H18: 602600 | J18: B1 | K18: 376330.41 | M18: B1 | N18: 40000 | Q18: B1 | R18: 376330.41 | X18: B4 | Y18: 4142411.8
A19: D5 | B19: 2978061.8 | D19: B1 | E19: 495000 | G19: B2 | H19: 1823245.5 | J19: B2 | K19: 376330.41 | M19: B2 | N19: 120000 | Q19: B2 | R19: 376330.41 | X19: D2 | Y19: 4130022.7
A20: D4 | B20: 3523220.7 | D20: B2 | E20: 1497400 | G20: B4 | H20: 1922400 | J20: B3 | K20: 376330.41 | M20: B3 | N20: 90000 | Q20: B3 | R20: 376330.41 | X20: B2 | Y20: 4060657.3
A21: D3 | B21: 3875608.2 | D21: B3 | E21: 1867600 | G21: B5 | H21: 2168021.5 | J21: B4 | K21: 376330.41 | M21: B4 | N21: 70000 | Q21: B4 | R21: 376330.41 | X21: D3 | Y21: 3875608.2
A22: D2 | B22: 4130022.7 | D22: B4 | E22: 1525000 | G22: B6 | H22: 1615950 | J22: B5 | K22: 376330.41 | M22: B5 | N22: 130000 | Q22: B5 | R22: 376330.41 | X22: C6 | Y22: 3765920.7
A23: D1 | B23: 3037750.8 | D23: B5 | E23: 1584000 | G23: B7 | H23: 1766600 | J23: B6 | K23: 376330.41 | M23: B6 | N23: 110000 | Q23: B6 | R23: 376330.41 | X23: C5 | Y23: 3706051.6
A24: Construction | B24: 813000 | D24: B6 | E24: 729500 | G24: B8 | H24: 1043450 | J24: B7 | K24: 376330.41 | M24: B7 | N24: 120000 | Q24: B7 | R24: 376330.41 | X24: D4 | Y24: 3523220.7
A25: C8 | B25: 2212592.8 | D25: B7 | E25: 440000 | G25: C1 | H25: 2143615.8 | J25: B8 | K25: 376330.41 | M25: B8 | N25: 130000 | Q25: B8 | R25: 376330.41 | X25: D7 | Y25: 3383466.9
... A27: C6 | B27: 3765920.7 | D27: C1 | E27: 644300 | G27: C3 | H27: 1800830 | J27: C2 | K27: 376330.41 | M27: C2 | N27: 120000 | Q27: C2 | R27: 376330.41 | X27: B6 | Y27: 3306751.1
A28: C5 | B28: 3706051.6 | D28: C2 | E28: 860000 | G28: C4 | H28: 1517943.2 | J28: C3 | K28: 250376.4 | M28: C3 | N28: 157500 | O28: 4750 | Q28: C3 | R28: 250376.4 | X28: C1 | Y28: 3269746.2
A29: C4 | B29: 4427955 | D29: C3 | E29: 1856450 | G29: C5 | H29: 1993789.8 | J29: C4 | K29: 376330.41 | M29: C4 | N29: 90000 | Q29: C4 | R29: 376330.41 | X29: B8 | Y29: 3252961.8
A30: C3 | B30: 4724412.5 | D30: C4 | E30: 2200000 | G30: C6 | H30: 1480590.2 | J30: C5 | K30: 376330.41 | M30: C5 | N30: 177500 | O30: 4750 | Q30: C5 | R30: 376330.41 | X30: A1 | Y30: 3128086.7
A31: C2 | B31: 3074027.7 | D31: C5 | E31: 910000 | G31: C7 | H31: 602600 | J31: C6 | K31: 376330.41 | M31: C6 | N31: 120000 | Q31: C6 | R31: 376330.41 | X31: C2 | Y31: 3074027.7
A32: C1 | B32: 3269746.2 | D32: C6 | E32: 1783000 | G32: C8 | H32: 602600 | J32: C7 | K32: 376330.41 | M32: C7 | N32: 120000 | Q32: C7 | R32: 376330.41 | X32: I3 | Y32: 3041775.8
A33: B8 | B33: 3252961.8 | D33: C7 | E33: 920000 | G33: D1 | H33: 1912100 | J33: C8 | K33: 376330.41 | M33: C8 | N33: 20000 | Q33: C8 | R33: 376330.41 | X33: D1 | Y33: 3037750.8
A34: B7 | B34: 2708930.4 | D34: C8 | E34: 900000 | G34: D2 | H34: 1474910.9 | J34: D1 | K34: 376330.41 | M34: Common Area | N34: 10000 | Q34: D1 | R34: 376330.41 | X34: D5 | Y34: 2978061.8
A35: B6 | B35: 3306751.1 | D35: D1 | E35: 553900 | G35: D3 | H35: 1389433.9 | J35: D2 | K35: 376330.41 | M35: D1 | N35: 130000 | Q35: D2 | R35: 376330.41 | X35: D8 | Y35: 2924762.9
A36: B5 | B36: 4502033.3 | D36: D2 | E36: 1915100 | G36: D4 | H36: 1646558.9 | J36: D3 | K36: 376330.41 | M36: D2 | N36: 120000 | Q36: D3 | R36: 376330.41 | X36: APH | Y36: 2798631.4
A37: B4 | B37: 4142411.8 | D37: D3 | E37: 1353500 | G37: D5 | H37: 1324950 | J37: D4 | K37: 376330.41 | M37: D3 | N37: 110000 | Q37: D4 | R37: 376330.41 | X37: B7 | Y37: 2708930.4
A38: B3 | B38: 2339930.4 | D38: D4 | E38: 1118900 | G38: D6 | H38: 3061546.5 | J38: D5 | K38: 376330.41 | M38: D4 | N38: 138250 | Q38: D5 | R38: 376330.41 | X38: A7 | Y38: 2437111.8
A39: B2 | B39: 4060657.3 | D39: D5 | E39: 913100 | G39: D7 | H39: 1705636.4 | J39: D6 | K39: 752660.82 | M39: D5 | N39: 120000 | Q39: D6 | R39: 752660.82 | X39: B3 | Y39: 2339930.4
A40: B1 | B40: 1762611.8 | D40: D6 | E40: 2003300 | G40: D8 | H40: 1621100 | J40: D7 | K40: 376330.41 | M40: D6 | N40: 260000 | Q40: D7 | R40: 376330.41 | X40: C7 | Y40: 2262611.8
A41: APH | B41: 2798631.4 | D41: D7 | E41: 1165500 | G41: DPH | H41: 1330100 | J41: D8 | K41: 376330.41 | M41: D7 | N41: 130000 | Q41: D8 | R41: 376330.41 | X41: C8 | Y41: 2212592.8
A42: A8 | B42: 4793920.7 | D42: D8 | E42: 560000 | G42: I1 | H42: 1330460 | J42: DPH | K42: 376330.41 | M42: D8 | N42: 110000 | Q42: DPH | R42: 376330.41 | X42: A5 | Y42: 2158507.8
... A46: A3 | B46: 1648884.2 | D46: I3 | E46: 1185000 | G46: Grand Total | H46: 51883291 | J46: I4 | K46: 376330.41 | M46: I3 | N46: 80000 | Q46: I4 | R46: 376330.41 | X46: Office | Y46: 1096200
A47: A2 | B47: 2006930.4 | D47: I4 | E47: 1220000 | J47: Grand Total | K47: 13049481 | M47: I4 | N47: 80000 | Q47: Grand Total | R47: 13049481 | X47: Construction | Y47: 813000
A48: A1 | B48: 3128086.7 | D48: Office | E48: 1090200 | M48: Grand Total | N48: 3853250 | O48: 9500 | X48: A4 | Y48: 699412.4
A49: Grand Total | B49: 1.2685989e+08 | D49: Grand Total | E49: 49145559 | X49: Grand Total | Y49: 1.2685989e+08

Sheet Dashboards
Z89: Total Revenue | AA89: =GETPIVOTDATA("Total Price",'Pivot Tables'!$X$9) -> 1.2685989e+08
Z90: Electricity | AA90: =GETPIVOTDATA("Total Price",'Pivot Tables'!$D$9,"Bill","Electricity Recharge") -> 49145559
Z91: Service charge | AA91: =GETPIVOTDATA("Total Price",'Pivot Tables'!$G$9,"Bill","Service Charge") -> 51883291
Z92: Fixed charge | AA92: =GETPIVOTDATA("Total Price",'Pivot Tables'!$J$9,"Bill","Fixed Charge") -> 13049481
Z93: Water Bill | AA93: =GETPIVOTDATA("Total Price",'Pivot Tables'!$M$9,"Bill","Water Bill") -> 3853250
Z94: Top Paying Unit | AA94: =INDEX('Pivot Tables'!A10:A48, MATCH(MAX('Pivot Tables'!B10:B48), 'Pivot Tables'!B10:B48, 0)) -> D6
Z95: Lowest Paying Unit | AA95: =INDEX('Pivot Tables'!A11:A49, MATCH(MIN('Pivot Tables'!B11:B49), 'Pivot Tables'!B11:B49, 0)) -> A4
